credio/cli/actions/__init__.py
credio/cli/actions/artifact.py
credio/cli/actions/auth.py
credio/cli/actions/competition.py
credio/cli/actions/config.py
credio/cli/actions/gateway.py
credio/cli/actions/proxy.py
credio/cli/actions/zkml.py
credio/cli/entrypoint.py
credio/config/__init__.py
credio/config/file.py
credio/config/ioc.py
credio/config/ipfs.py
credio/config/store.py
credio/config/value.py
credio/util/collection.py
credio/util/log.py
credio/util/type.py
untangled_credio_cli-24.7.25.dist-info/METADATA
untangled_credio_cli-24.7.25.dist-info/WHEEL
untangled_credio_cli-24.7.25.dist-info/entry_points.txt
untangled_credio_cli-24.7.25.dist-info/RECORD
