Metadata-Version: 2.1
Name: untangled-credio-cli
Version: 24.7.25
Summary: A command-line tool to build everything.
License: MIT
Author: Tuan
Author-email: tuan@untangled.finance
Requires-Python: ==3.11.9
Classifier: License :: OSI Approved :: MIT License
Classifier: Programming Language :: Python :: 3
Requires-Dist: aiofile (>=3.8.8,<4.0.0)
Requires-Dist: aiohttp (>=3.9.5,<4.0.0)
Requires-Dist: ipfshttpclient (>=0.7.0,<0.8.0)
Requires-Dist: jmespath (>=1.0.1,<2.0.0)
Requires-Dist: paramiko (>=3.4.0,<4.0.0)
Requires-Dist: pyinstaller (==6.8.0)
Requires-Dist: rich (>=13.7.1,<14.0.0)
Requires-Dist: typer (>=0.12.3,<0.13.0)
